[
    {
        "rank": 1,
        "athlete_id": 41554194,
        "velocity": 3.0992077509209266,
        "elev_gain": 398,
        "num_activities": 4,
        "moving_time": 19817,
        "distance": 61417,
        "best_activities_distance": 26217.240234375,
        "best_activities_distance_activity_id": 10593182136,
        "athlete_firstname": "Stephen",
        "athlete_lastname": "H."
    },
    {
        "rank": 2,
        "athlete_id": 30533086,
        "velocity": 3.395450144044431,
        "elev_gain": 57,
        "num_activities": 5,
        "moving_time": 15029,
        "distance": 51030.22021484375,
        "best_activities_distance": 13098.990234375,
        "best_activities_distance_activity_id": 10603000676,
        "athlete_firstname": "Nicola",
        "athlete_lastname": "M."
    },
    {
        "rank": 3,
        "athlete_id": 50955145,
        "velocity": 2.8395941591653027,
        "elev_gain": 79,
        "num_activities": 5,
        "moving_time": 15275,
        "distance": 43374.80078125,
        "best_activities_distance": 13013.3603515625,
        "best_activities_distance_activity_id": 10596687130,
        "athlete_firstname": "Miguel",
        "athlete_lastname": "V."
    },
    {
        "rank": 4,
        "athlete_id": 4133813,
        "velocity": 3.3994167352603895,
        "elev_gain": 130.37523746490479,
        "num_activities": 6,
        "moving_time": 11418,
        "distance": 38814.540283203125,
        "best_activities_distance": 11309.330078125,
        "best_activities_distance_activity_id": 10561440576,
        "athlete_firstname": "Thomas",
        "athlete_lastname": "K."
    },
    {
        "rank": 5,
        "athlete_id": 1908509,
        "velocity": 3.303014891163058,
        "elev_gain": 184,
        "num_activities": 3,
        "moving_time": 11732,
        "distance": 38750.970703125,
        "best_activities_distance": 21250.970703125,
        "best_activities_distance_activity_id": 10599173570,
        "athlete_firstname": "Josh",
        "athlete_lastname": "B."
    },
    {
        "rank": 6,
        "athlete_id": 21014702,
        "velocity": 3.0947699897536856,
        "elev_gain": 390,
        "num_activities": 3,
        "moving_time": 12413,
        "distance": 38415.3798828125,
        "best_activities_distance": 21183.080078125,
        "best_activities_distance_activity_id": 10561620276,
        "athlete_firstname": "Tom",
        "athlete_lastname": "M."
    },
    {
        "rank": 7,
        "athlete_id": 21539219,
        "velocity": 3.269081487973096,
        "elev_gain": 241.9417495727539,
        "num_activities": 3,
        "moving_time": 10965,
        "distance": 35845.478515625,
        "best_activities_distance": 17143.5390625,
        "best_activities_distance_activity_id": 10599077142,
        "athlete_firstname": "Dave",
        "athlete_lastname": "H."
    },
    {
        "rank": 8,
        "athlete_id": 10514550,
        "velocity": 2.608090265012255,
        "elev_gain": 138.96725845336914,
        "num_activities": 4,
        "moving_time": 12750,
        "distance": 33253.15087890625,
        "best_activities_distance": 14638.400390625,
        "best_activities_distance_activity_id": 10599729122,
        "athlete_firstname": "Celine",
        "athlete_lastname": "S."
    },
    {
        "rank": 9,
        "athlete_id": 58554127,
        "velocity": 2.8603248033280164,
        "elev_gain": 190.04400062561035,
        "num_activities": 4,
        "moving_time": 10775,
        "distance": 30819.999755859375,
        "best_activities_distance": 16029.7998046875,
        "best_activities_distance_activity_id": 10600138050,
        "athlete_firstname": "Dan",
        "athlete_lastname": "B."
    },
    {
        "rank": 10,
        "athlete_id": 2926865,
        "velocity": 3.050888119482086,
        "elev_gain": 108.5857162475586,
        "num_activities": 2,
        "moving_time": 9741,
        "distance": 29718.701171875,
        "best_activities_distance": 21189.201171875,
        "best_activities_distance_activity_id": 10600144728,
        "athlete_firstname": "Daniel",
        "athlete_lastname": "H."
    },
    {
        "rank": 11,
        "athlete_id": 13680714,
        "velocity": 2.9037420676514563,
        "elev_gain": 111,
        "num_activities": 4,
        "moving_time": 9615,
        "distance": 27919.47998046875,
        "best_activities_distance": 10013.580078125,
        "best_activities_distance_activity_id": 10571606341,
        "athlete_firstname": "Mike",
        "athlete_lastname": "d."
    },
    {
        "rank": 12,
        "athlete_id": 57678895,
        "velocity": 2.9504794509095773,
        "elev_gain": 455,
        "num_activities": 3,
        "moving_time": 9345,
        "distance": 27572.23046875,
        "best_activities_distance": 14022.2001953125,
        "best_activities_distance_activity_id": 10569551004,
        "athlete_firstname": "Nico",
        "athlete_lastname": "M."
    },
    {
        "rank": 13,
        "athlete_id": 74735797,
        "velocity": 2.7430949099207607,
        "elev_gain": 144.79618644714355,
        "num_activities": 2,
        "moving_time": 8692,
        "distance": 23842.98095703125,
        "best_activities_distance": 17111.630859375,
        "best_activities_distance_activity_id": 10599687554,
        "athlete_firstname": "Blane",
        "athlete_lastname": "M."
    },
    {
        "rank": 14,
        "athlete_id": 7347389,
        "velocity": 2.8501833051325436,
        "elev_gain": 45,
        "num_activities": 2,
        "moving_time": 7092,
        "distance": 20213.5,
        "best_activities_distance": 14864.169921875,
        "best_activities_distance_activity_id": 10563908075,
        "athlete_firstname": "David",
        "athlete_lastname": "T."
    },
    {
        "rank": 15,
        "athlete_id": 52884370,
        "velocity": 2.9698234932953627,
        "elev_gain": 110.26698207855225,
        "num_activities": 4,
        "moving_time": 6798,
        "distance": 20188.860107421875,
        "best_activities_distance": 8006.25,
        "best_activities_distance_activity_id": 10593609461,
        "athlete_firstname": "Mairead",
        "athlete_lastname": "H."
    },
    {
        "rank": 16,
        "athlete_id": 29943981,
        "velocity": 3.6472238960628887,
        "elev_gain": 55,
        "num_activities": 3,
        "moving_time": 5468,
        "distance": 19943.020263671875,
        "best_activities_distance": 11006.990234375,
        "best_activities_distance_activity_id": 10595444910,
        "athlete_firstname": "Paul",
        "athlete_lastname": "J."
    },
    {
        "rank": 17,
        "athlete_id": 37776583,
        "velocity": 2.885233052038064,
        "elev_gain": 53,
        "num_activities": 3,
        "moving_time": 6673,
        "distance": 19253.16015625,
        "best_activities_distance": 8130.0498046875,
        "best_activities_distance_activity_id": 10580220620,
        "athlete_firstname": "Lydia",
        "athlete_lastname": "W."
    },
    {
        "rank": 18,
        "athlete_id": 115586574,
        "velocity": 3.303806875458211,
        "elev_gain": 28.60921859741211,
        "num_activities": 2,
        "moving_time": 5456,
        "distance": 18025.5703125,
        "best_activities_distance": 11015.150390625,
        "best_activities_distance_activity_id": 10580799188,
        "athlete_firstname": "Lewis",
        "athlete_lastname": "J."
    },
    {
        "rank": 19,
        "athlete_id": 24392844,
        "velocity": 3.0205878852840327,
        "elev_gain": 35.36154794692993,
        "num_activities": 3,
        "moving_time": 5851,
        "distance": 17673.459716796875,
        "best_activities_distance": 8001.759765625,
        "best_activities_distance_activity_id": 10580549073,
        "athlete_firstname": "Hannah",
        "athlete_lastname": "M."
    },
    {
        "rank": 20,
        "athlete_id": 4652315,
        "velocity": 3.033386094018702,
        "elev_gain": 212,
        "num_activities": 3,
        "moving_time": 5815,
        "distance": 17639.14013671875,
        "best_activities_distance": 7257.60986328125,
        "best_activities_distance_activity_id": 10593873626,
        "athlete_firstname": "Joe",
        "athlete_lastname": "E."
    },
    {
        "rank": 21,
        "athlete_id": 11827446,
        "velocity": 2.8121346109220298,
        "elev_gain": 95.60000228881836,
        "num_activities": 2,
        "moving_time": 5050,
        "distance": 14201.27978515625,
        "best_activities_distance": 7325.18994140625,
        "best_activities_distance_activity_id": 10563406306,
        "athlete_firstname": "Mark",
        "athlete_lastname": "G."
    },
    {
        "rank": 22,
        "athlete_id": 22467435,
        "velocity": 3.614077349790593,
        "elev_gain": 67,
        "num_activities": 1,
        "moving_time": 3880,
        "distance": 14022.6201171875,
        "best_activities_distance": 14022.6201171875,
        "best_activities_distance_activity_id": 10581767396,
        "athlete_firstname": "Wilson",
        "athlete_lastname": "L."
    },
    {
        "rank": 23,
        "athlete_id": 5059389,
        "velocity": 3.5225749156162016,
        "elev_gain": 137,
        "num_activities": 1,
        "moving_time": 3907,
        "distance": 13762.7001953125,
        "best_activities_distance": 13762.7001953125,
        "best_activities_distance_activity_id": 10600728408,
        "athlete_firstname": "Stephen",
        "athlete_lastname": "M."
    },
    {
        "rank": 24,
        "athlete_id": 90059876,
        "velocity": 2.6793841222549544,
        "elev_gain": 26.426057815551758,
        "num_activities": 1,
        "moving_time": 3734,
        "distance": 10004.8203125,
        "best_activities_distance": 10004.8203125,
        "best_activities_distance_activity_id": 10588126987,
        "athlete_firstname": "Nitika",
        "athlete_lastname": "B."
    },
    {
        "rank": 25,
        "athlete_id": 18514233,
        "velocity": 3.2256613140335553,
        "elev_gain": 57.19862365722656,
        "num_activities": 2,
        "moving_time": 3077,
        "distance": 9925.35986328125,
        "best_activities_distance": 5002.02001953125,
        "best_activities_distance_activity_id": 10561476646,
        "athlete_firstname": "Freddie",
        "athlete_lastname": "M."
    },
    {
        "rank": 26,
        "athlete_id": 1326614,
        "velocity": 2.792405939366079,
        "elev_gain": 90.40001487731934,
        "num_activities": 2,
        "moving_time": 3433,
        "distance": 9586.32958984375,
        "best_activities_distance": 5051.009765625,
        "best_activities_distance_activity_id": 10599898632,
        "athlete_firstname": "Mark",
        "athlete_lastname": "T."
    },
    {
        "rank": 27,
        "athlete_id": 31691560,
        "velocity": 3.4545814523415386,
        "elev_gain": 44,
        "num_activities": 2,
        "moving_time": 2473,
        "distance": 8543.179931640625,
        "best_activities_distance": 5436.0400390625,
        "best_activities_distance_activity_id": 10561676493,
        "athlete_firstname": "Jonathan",
        "athlete_lastname": "S."
    },
    {
        "rank": 28,
        "athlete_id": 103649447,
        "velocity": 2.618813247774738,
        "elev_gain": 0,
        "num_activities": 3,
        "moving_time": 3244,
        "distance": 8495.43017578125,
        "best_activities_distance": 5125.43017578125,
        "best_activities_distance_activity_id": 10592695690,
        "athlete_firstname": "Hannah",
        "athlete_lastname": "D."
    },
    {
        "rank": 29,
        "athlete_id": 8389301,
        "velocity": 2.6000226088250726,
        "elev_gain": 89,
        "num_activities": 1,
        "moving_time": 3097,
        "distance": 8052.27001953125,
        "best_activities_distance": 8052.27001953125,
        "best_activities_distance_activity_id": 10601309313,
        "athlete_firstname": "Andrew",
        "athlete_lastname": "M."
    },
    {
        "rank": 30,
        "athlete_id": 121747391,
        "velocity": 2.568643756844176,
        "elev_gain": 2.174999952316284,
        "num_activities": 1,
        "moving_time": 3082,
        "distance": 7916.56005859375,
        "best_activities_distance": 7916.56005859375,
        "best_activities_distance_activity_id": 10583425624,
        "athlete_firstname": "Jana",
        "athlete_lastname": "G."
    },
    {
        "rank": 31,
        "athlete_id": 72151749,
        "velocity": 3.333862467087029,
        "elev_gain": 20.58571434020996,
        "num_activities": 1,
        "moving_time": 2255,
        "distance": 7517.85986328125,
        "best_activities_distance": 7517.85986328125,
        "best_activities_distance_activity_id": 10583892102,
        "athlete_firstname": "Adon",
        "athlete_lastname": "L."
    },
    {
        "rank": 32,
        "athlete_id": 11743280,
        "velocity": 3.4841082688823857,
        "elev_gain": 10.827940940856934,
        "num_activities": 1,
        "moving_time": 1794,
        "distance": 6250.490234375,
        "best_activities_distance": 6250.490234375,
        "best_activities_distance_activity_id": 10598725379,
        "athlete_firstname": "Hatty",
        "athlete_lastname": "M."
    },
    {
        "rank": 33,
        "athlete_id": 122644152,
        "velocity": 2.7210238004623366,
        "elev_gain": 8.11336612701416,
        "num_activities": 1,
        "moving_time": 2217,
        "distance": 6032.509765625,
        "best_activities_distance": 6032.509765625,
        "best_activities_distance_activity_id": 10567770456,
        "athlete_firstname": "Owen",
        "athlete_lastname": "K."
    },
    {
        "rank": 34,
        "athlete_id": 56485102,
        "velocity": 2.5654350784495246,
        "elev_gain": 6.894705772399902,
        "num_activities": 3,
        "moving_time": 2287,
        "distance": 5867.1500244140625,
        "best_activities_distance": 2032.27001953125,
        "best_activities_distance_activity_id": 10567824981,
        "athlete_firstname": "Sarah",
        "athlete_lastname": "A."
    },
    {
        "rank": 35,
        "athlete_id": 18880192,
        "velocity": 2.826856722850363,
        "elev_gain": 39.3033332824707,
        "num_activities": 1,
        "moving_time": 1791,
        "distance": 5062.900390625,
        "best_activities_distance": 5062.900390625,
        "best_activities_distance_activity_id": 10592960405,
        "athlete_firstname": "Jemma",
        "athlete_lastname": "S."
    },
    {
        "rank": 36,
        "athlete_id": 51717132,
        "velocity": 2.301157193194761,
        "elev_gain": 20.30714225769043,
        "num_activities": 1,
        "moving_time": 2195,
        "distance": 5051.0400390625,
        "best_activities_distance": 5051.0400390625,
        "best_activities_distance_activity_id": 10593345023,
        "athlete_firstname": "Kirsten",
        "athlete_lastname": "A."
    },
    {
        "rank": 37,
        "athlete_id": 80777288,
        "velocity": 2.7518220642389526,
        "elev_gain": 7.980000019073486,
        "num_activities": 1,
        "moving_time": 1833,
        "distance": 5044.08984375,
        "best_activities_distance": 5044.08984375,
        "best_activities_distance_activity_id": 10600079908,
        "athlete_firstname": "Lorna",
        "athlete_lastname": "C."
    },
    {
        "rank": 38,
        "athlete_id": 29577503,
        "velocity": 2.905983741614974,
        "elev_gain": 28.760604858398438,
        "num_activities": 1,
        "moving_time": 1733,
        "distance": 5036.06982421875,
        "best_activities_distance": 5036.06982421875,
        "best_activities_distance_activity_id": 10569429840,
        "athlete_firstname": "Ian",
        "athlete_lastname": "C."
    },
    {
        "rank": 39,
        "athlete_id": 6323028,
        "velocity": 2.629435859130094,
        "elev_gain": 26.833145141601562,
        "num_activities": 1,
        "moving_time": 1914,
        "distance": 5032.740234375,
        "best_activities_distance": 5032.740234375,
        "best_activities_distance_activity_id": 10592613803,
        "athlete_firstname": "Sophie",
        "athlete_lastname": "D."
    },
    {
        "rank": 40,
        "athlete_id": 100745857,
        "velocity": 2.9229904602621204,
        "elev_gain": 36,
        "num_activities": 1,
        "moving_time": 1712,
        "distance": 5004.15966796875,
        "best_activities_distance": 5004.15966796875,
        "best_activities_distance_activity_id": 10597594697,
        "athlete_firstname": "Alison",
        "athlete_lastname": "L."
    },
    {
        "rank": 41,
        "athlete_id": 2095180,
        "velocity": 4.218657210066512,
        "elev_gain": 14,
        "num_activities": 1,
        "moving_time": 1184,
        "distance": 4994.89013671875,
        "best_activities_distance": 4994.89013671875,
        "best_activities_distance_activity_id": 10592557360,
        "athlete_firstname": "David",
        "athlete_lastname": "S."
    }
]
