[
    {
        "rank": 1,
        "athlete_id": 5059389,
        "velocity": 3.52296951714281,
        "elev_gain": 994,
        "num_activities": 7,
        "moving_time": 37935,
        "distance": 133643.8486328125,
        "best_activities_distance": 36053.48828125,
        "best_activities_distance_activity_id": 9505235949,
        "athlete_firstname": "Stephen",
        "athlete_lastname": "M."
    },
    {
        "rank": 2,
        "athlete_id": 5915073,
        "velocity": 3.1970076662279037,
        "elev_gain": 749,
        "num_activities": 6,
        "moving_time": 24382,
        "distance": 77949.44091796875,
        "best_activities_distance": 32632.470703125,
        "best_activities_distance_activity_id": 9504903702,
        "athlete_firstname": "Sham",
        "athlete_lastname": "H."
    },
    {
        "rank": 3,
        "athlete_id": 13680714,
        "velocity": 3.0688227594011948,
        "elev_gain": 221,
        "num_activities": 6,
        "moving_time": 21593,
        "distance": 66265.08984375,
        "best_activities_distance": 20306.830078125,
        "best_activities_distance_activity_id": 9498506188,
        "athlete_firstname": "Mike",
        "athlete_lastname": "d."
    },
    {
        "rank": 4,
        "athlete_id": 30533086,
        "velocity": 3.3407259018099262,
        "elev_gain": 105,
        "num_activities": 8,
        "moving_time": 15857,
        "distance": 52973.890625,
        "best_activities_distance": 22960.55078125,
        "best_activities_distance_activity_id": 9498243821,
        "athlete_firstname": "Nicola",
        "athlete_lastname": "M."
    },
    {
        "rank": 5,
        "athlete_id": 7347389,
        "velocity": 2.8679697367036208,
        "elev_gain": 303,
        "num_activities": 4,
        "moving_time": 17815,
        "distance": 51092.880859375,
        "best_activities_distance": 15359.7099609375,
        "best_activities_distance_activity_id": 9480317200,
        "athlete_firstname": "David",
        "athlete_lastname": "T."
    },
    {
        "rank": 6,
        "athlete_id": 4133813,
        "velocity": 3.542084618205273,
        "elev_gain": 203.6166706085205,
        "num_activities": 6,
        "moving_time": 14147,
        "distance": 50109.87109375,
        "best_activities_distance": 11445.8603515625,
        "best_activities_distance_activity_id": 9485628219,
        "athlete_firstname": "Thomas",
        "athlete_lastname": "K."
    },
    {
        "rank": 7,
        "athlete_id": 50955145,
        "velocity": 2.816151273909889,
        "elev_gain": 76,
        "num_activities": 4,
        "moving_time": 13181,
        "distance": 37119.68994140625,
        "best_activities_distance": 12027.3701171875,
        "best_activities_distance_activity_id": 9508804780,
        "athlete_firstname": "Miguel",
        "athlete_lastname": "V."
    },
    {
        "rank": 8,
        "athlete_id": 2926865,
        "velocity": 2.945337361395569,
        "elev_gain": 165.62158393859863,
        "num_activities": 5,
        "moving_time": 11352,
        "distance": 33435.4697265625,
        "best_activities_distance": 10014.2197265625,
        "best_activities_distance_activity_id": 9476737045,
        "athlete_firstname": "Daniel",
        "athlete_lastname": "H."
    },
    {
        "rank": 9,
        "athlete_id": 2095180,
        "velocity": 3.697167682464906,
        "elev_gain": 118,
        "num_activities": 4,
        "moving_time": 8869,
        "distance": 32790.18017578125,
        "best_activities_distance": 12794.16015625,
        "best_activities_distance_activity_id": 9504333136,
        "athlete_firstname": "David",
        "athlete_lastname": "S."
    },
    {
        "rank": 10,
        "athlete_id": 61351589,
        "velocity": 3.273621850522653,
        "elev_gain": 182.63437271118164,
        "num_activities": 3,
        "moving_time": 8873,
        "distance": 29046.8466796875,
        "best_activities_distance": 10574.0869140625,
        "best_activities_distance_activity_id": 9480928571,
        "athlete_firstname": "Paul",
        "athlete_lastname": "B."
    },
    {
        "rank": 11,
        "athlete_id": 58554127,
        "velocity": 2.9146906265621326,
        "elev_gain": 35.20400023460388,
        "num_activities": 3,
        "moving_time": 8502,
        "distance": 24780.69970703125,
        "best_activities_distance": 10099,
        "best_activities_distance_activity_id": 9472470899,
        "athlete_firstname": "Dan",
        "athlete_lastname": "B."
    },
    {
        "rank": 12,
        "athlete_id": 7347308,
        "velocity": 2.685381186145776,
        "elev_gain": 90.41718196868896,
        "num_activities": 3,
        "moving_time": 9115,
        "distance": 24477.24951171875,
        "best_activities_distance": 10000.330078125,
        "best_activities_distance_activity_id": 9494805532,
        "athlete_firstname": "Steve",
        "athlete_lastname": "M."
    },
    {
        "rank": 13,
        "athlete_id": 11743280,
        "velocity": 3.5498434184289476,
        "elev_gain": 32.218063831329346,
        "num_activities": 4,
        "moving_time": 6833,
        "distance": 24256.080078125,
        "best_activities_distance": 8009.419921875,
        "best_activities_distance_activity_id": 9472289600,
        "athlete_firstname": "Hatty",
        "athlete_lastname": "M."
    },
    {
        "rank": 14,
        "athlete_id": 21539219,
        "velocity": 3.3079836088046375,
        "elev_gain": 102.12446594238281,
        "num_activities": 2,
        "moving_time": 6383,
        "distance": 21114.859375,
        "best_activities_distance": 12271.58984375,
        "best_activities_distance_activity_id": 9504139515,
        "athlete_firstname": "Dave",
        "athlete_lastname": "H."
    },
    {
        "rank": 15,
        "athlete_id": 103056769,
        "velocity": 2.9025928111740416,
        "elev_gain": 190.98297309875488,
        "num_activities": 3,
        "moving_time": 6599,
        "distance": 19154.2099609375,
        "best_activities_distance": 7515.77001953125,
        "best_activities_distance_activity_id": 9497745229,
        "athlete_firstname": "Marina",
        "athlete_lastname": "E."
    },
    {
        "rank": 16,
        "athlete_id": 51717132,
        "velocity": 2.5914546759388526,
        "elev_gain": 112,
        "num_activities": 3,
        "moving_time": 7163,
        "distance": 18562.58984375,
        "best_activities_distance": 8395.1796875,
        "best_activities_distance_activity_id": 9499083048,
        "athlete_firstname": "Kirsten",
        "athlete_lastname": "A."
    },
    {
        "rank": 17,
        "athlete_id": 29943981,
        "velocity": 3.687725631768953,
        "elev_gain": 64,
        "num_activities": 3,
        "moving_time": 4986,
        "distance": 18387,
        "best_activities_distance": 7282.26025390625,
        "best_activities_distance_activity_id": 9505297600,
        "athlete_firstname": "Paul",
        "athlete_lastname": "J."
    },
    {
        "rank": 18,
        "athlete_id": 52884370,
        "velocity": 3.107844445435954,
        "elev_gain": 57.2771430015564,
        "num_activities": 4,
        "moving_time": 5822,
        "distance": 18093.870361328125,
        "best_activities_distance": 6002.18017578125,
        "best_activities_distance_activity_id": 9498866413,
        "athlete_firstname": "Mairead",
        "athlete_lastname": "H."
    },
    {
        "rank": 19,
        "athlete_id": 18514233,
        "velocity": 3.3036542585211697,
        "elev_gain": 108.31636333465576,
        "num_activities": 4,
        "moving_time": 5016,
        "distance": 16571.129760742188,
        "best_activities_distance": 5050.58984375,
        "best_activities_distance_activity_id": 9498026073,
        "athlete_firstname": "Freddie",
        "athlete_lastname": "M."
    },
    {
        "rank": 20,
        "athlete_id": 80777288,
        "velocity": 2.8956477096226734,
        "elev_gain": 24.84333324432373,
        "num_activities": 3,
        "moving_time": 5211,
        "distance": 15089.22021484375,
        "best_activities_distance": 5035.6201171875,
        "best_activities_distance_activity_id": 9500359925,
        "athlete_firstname": "Lorna",
        "athlete_lastname": "C."
    },
    {
        "rank": 21,
        "athlete_id": 24392844,
        "velocity": 3.194321882496002,
        "elev_gain": 25.703214645385742,
        "num_activities": 3,
        "moving_time": 4690,
        "distance": 14981.36962890625,
        "best_activities_distance": 5013.3798828125,
        "best_activities_distance_activity_id": 9467478553,
        "athlete_firstname": "Hannah",
        "athlete_lastname": "M."
    },
    {
        "rank": 22,
        "athlete_id": 103649447,
        "velocity": 2.838904707731904,
        "elev_gain": 0,
        "num_activities": 3,
        "moving_time": 4711,
        "distance": 13374.080078125,
        "best_activities_distance": 5064.080078125,
        "best_activities_distance_activity_id": 9498247548,
        "athlete_firstname": "Hannah",
        "athlete_lastname": "D."
    },
    {
        "rank": 23,
        "athlete_id": 41554194,
        "velocity": 2.897120253710892,
        "elev_gain": 90,
        "num_activities": 3,
        "moving_time": 4299,
        "distance": 12454.719970703125,
        "best_activities_distance": 5011.52001953125,
        "best_activities_distance_activity_id": 9498141476,
        "athlete_firstname": "Stephen",
        "athlete_lastname": "H."
    },
    {
        "rank": 24,
        "athlete_id": 44138705,
        "velocity": 2.7338182325487015,
        "elev_gain": 67,
        "num_activities": 2,
        "moving_time": 4235,
        "distance": 11577.72021484375,
        "best_activities_distance": 6733.81005859375,
        "best_activities_distance_activity_id": 9508142715,
        "athlete_firstname": "Ellie",
        "athlete_lastname": "H."
    },
    {
        "rank": 25,
        "athlete_id": 4836255,
        "velocity": 2.9222658975751714,
        "elev_gain": 50,
        "num_activities": 2,
        "moving_time": 3941,
        "distance": 11516.64990234375,
        "best_activities_distance": 6381.06005859375,
        "best_activities_distance_activity_id": 9466210937,
        "athlete_firstname": "Pieter",
        "athlete_lastname": "L."
    },
    {
        "rank": 26,
        "athlete_id": 6323028,
        "velocity": 2.517710182133198,
        "elev_gain": 208.5615234375,
        "num_activities": 2,
        "moving_time": 4437,
        "distance": 11171.080078125,
        "best_activities_distance": 6208.27001953125,
        "best_activities_distance_activity_id": 9473726036,
        "athlete_firstname": "Sophie",
        "athlete_lastname": "D."
    },
    {
        "rank": 27,
        "athlete_id": 10514550,
        "velocity": 2.5993528699259967,
        "elev_gain": 24.021111488342285,
        "num_activities": 3,
        "moving_time": 4265,
        "distance": 11086.239990234375,
        "best_activities_distance": 5087.85009765625,
        "best_activities_distance_activity_id": 9498132602,
        "athlete_firstname": "Celine",
        "athlete_lastname": "S."
    },
    {
        "rank": 28,
        "athlete_id": 74735797,
        "velocity": 2.831134770374561,
        "elev_gain": 31.106666564941406,
        "num_activities": 2,
        "moving_time": 3701,
        "distance": 10478.02978515625,
        "best_activities_distance": 5478.27978515625,
        "best_activities_distance_activity_id": 9487014691,
        "athlete_firstname": "Blane",
        "athlete_lastname": "M."
    },
    {
        "rank": 29,
        "athlete_id": 100745857,
        "velocity": 2.430813463756678,
        "elev_gain": 23,
        "num_activities": 1,
        "moving_time": 4118,
        "distance": 10010.08984375,
        "best_activities_distance": 10010.08984375,
        "best_activities_distance_activity_id": 9504444855,
        "athlete_firstname": "Alison",
        "athlete_lastname": "L."
    },
    {
        "rank": 30,
        "athlete_id": 21014702,
        "velocity": 2.6495415903986275,
        "elev_gain": 99,
        "num_activities": 2,
        "moving_time": 3534,
        "distance": 9363.47998046875,
        "best_activities_distance": 5465.22998046875,
        "best_activities_distance_activity_id": 9493228470,
        "athlete_firstname": "Tom",
        "athlete_lastname": "M."
    },
    {
        "rank": 31,
        "athlete_id": 23175006,
        "velocity": 3.463386078304883,
        "elev_gain": 12.500824928283691,
        "num_activities": 1,
        "moving_time": 2519,
        "distance": 8724.26953125,
        "best_activities_distance": 8724.26953125,
        "best_activities_distance_activity_id": 9494002925,
        "athlete_firstname": "Aksel Strandgaard",
        "athlete_lastname": "H."
    },
    {
        "rank": 32,
        "athlete_id": 31691560,
        "velocity": 3.6371201149730727,
        "elev_gain": 23,
        "num_activities": 2,
        "moving_time": 2205,
        "distance": 8019.849853515625,
        "best_activities_distance": 5008.85986328125,
        "best_activities_distance_activity_id": 9485928764,
        "athlete_firstname": "Jonathan",
        "athlete_lastname": "S."
    },
    {
        "rank": 33,
        "athlete_id": 1803124,
        "velocity": 2.903439701616245,
        "elev_gain": 105,
        "num_activities": 1,
        "moving_time": 2413,
        "distance": 7006,
        "best_activities_distance": 7006,
        "best_activities_distance_activity_id": 9484097327,
        "athlete_firstname": "Neil",
        "athlete_lastname": "H."
    },
    {
        "rank": 34,
        "athlete_id": 115586574,
        "velocity": 3.34000953743443,
        "elev_gain": 7.259583473205566,
        "num_activities": 1,
        "moving_time": 2097,
        "distance": 7004,
        "best_activities_distance": 7004,
        "best_activities_distance_activity_id": 9498029667,
        "athlete_firstname": "Lewis",
        "athlete_lastname": "J."
    },
    {
        "rank": 35,
        "athlete_id": 40425808,
        "velocity": 2.3290597519832943,
        "elev_gain": 25.523977279663086,
        "num_activities": 1,
        "moving_time": 2978,
        "distance": 6935.93994140625,
        "best_activities_distance": 6935.93994140625,
        "best_activities_distance_activity_id": 9488570392,
        "athlete_firstname": "David",
        "athlete_lastname": "H."
    },
    {
        "rank": 36,
        "athlete_id": 57678895,
        "velocity": 3.103367763205239,
        "elev_gain": 55.8944206237793,
        "num_activities": 1,
        "moving_time": 1737,
        "distance": 5390.5498046875,
        "best_activities_distance": 5390.5498046875,
        "best_activities_distance_activity_id": 9474990809,
        "athlete_firstname": "Nico",
        "athlete_lastname": "M."
    },
    {
        "rank": 37,
        "athlete_id": 29577503,
        "velocity": 3.1351213304924244,
        "elev_gain": 16.903772354125977,
        "num_activities": 1,
        "moving_time": 1650,
        "distance": 5172.9501953125,
        "best_activities_distance": 5172.9501953125,
        "best_activities_distance_activity_id": 9473059793,
        "athlete_firstname": "Ian",
        "athlete_lastname": "C."
    },
    {
        "rank": 38,
        "athlete_id": 72291687,
        "velocity": 2.665528360473061,
        "elev_gain": 21.613691329956055,
        "num_activities": 1,
        "moving_time": 1921,
        "distance": 5120.47998046875,
        "best_activities_distance": 5120.47998046875,
        "best_activities_distance_activity_id": 9467133461,
        "athlete_firstname": "Chris",
        "athlete_lastname": "T."
    },
    {
        "rank": 39,
        "athlete_id": 7856161,
        "velocity": 3.049362089914945,
        "elev_gain": 103.41910552978516,
        "num_activities": 1,
        "moving_time": 1646,
        "distance": 5019.25,
        "best_activities_distance": 5019.25,
        "best_activities_distance_activity_id": 9465712546,
        "athlete_firstname": "Paul",
        "athlete_lastname": "W."
    },
    {
        "rank": 40,
        "athlete_id": 86083951,
        "velocity": 2.1994300317158046,
        "elev_gain": 26.179244995117188,
        "num_activities": 1,
        "moving_time": 2281,
        "distance": 5016.89990234375,
        "best_activities_distance": 5016.89990234375,
        "best_activities_distance_activity_id": 9503764979,
        "athlete_firstname": "ghislaine",
        "athlete_lastname": "a."
    },
    {
        "rank": 41,
        "athlete_id": 1696777,
        "velocity": 3.3062688617542846,
        "elev_gain": 36,
        "num_activities": 1,
        "moving_time": 1517,
        "distance": 5015.60986328125,
        "best_activities_distance": 5015.60986328125,
        "best_activities_distance_activity_id": 9504045105,
        "athlete_firstname": "Jack",
        "athlete_lastname": "C."
    },
    {
        "rank": 42,
        "athlete_id": 21676243,
        "velocity": 2.5,
        "elev_gain": 0,
        "num_activities": 1,
        "moving_time": 1920,
        "distance": 4800,
        "best_activities_distance": 4800,
        "best_activities_distance_activity_id": 9500893163,
        "athlete_firstname": "Hannah",
        "athlete_lastname": "A."
    },
    {
        "rank": 43,
        "athlete_id": 1908509,
        "velocity": 2.5539976219924543,
        "elev_gain": 59,
        "num_activities": 1,
        "moving_time": 1756,
        "distance": 4484.81982421875,
        "best_activities_distance": 4484.81982421875,
        "best_activities_distance_activity_id": 9497934907,
        "athlete_firstname": "Josh",
        "athlete_lastname": "B."
    },
    {
        "rank": 44,
        "athlete_id": 11827446,
        "velocity": 2.458272217761858,
        "elev_gain": 0,
        "num_activities": 1,
        "moving_time": 1771,
        "distance": 4353.60009765625,
        "best_activities_distance": 4353.60009765625,
        "best_activities_distance_activity_id": 9493335612,
        "athlete_firstname": "Mark",
        "athlete_lastname": "G."
    },
    {
        "rank": 45,
        "athlete_id": 1326614,
        "velocity": 3.2449403876500416,
        "elev_gain": 13.599998474121094,
        "num_activities": 4,
        "moving_time": 755,
        "distance": 2449.9299926757812,
        "best_activities_distance": 888.4099731445312,
        "best_activities_distance_activity_id": 9476566832,
        "athlete_firstname": "Mark",
        "athlete_lastname": "T."
    }
]
