[
    {
        "rank": 1,
        "athlete_id": 5059389,
        "velocity": 3.51111628117677,
        "elev_gain": 781,
        "num_activities": 9,
        "moving_time": 37553,
        "distance": 131852.94970703125,
        "best_activities_distance": 34134.1796875,
        "best_activities_distance_activity_id": 9685097323,
        "athlete_firstname": "Stephen",
        "athlete_lastname": "M."
    },
    {
        "rank": 2,
        "athlete_id": 5915073,
        "velocity": 3.1758150270216174,
        "elev_gain": 1066,
        "num_activities": 5,
        "moving_time": 24980,
        "distance": 79331.859375,
        "best_activities_distance": 32233.330078125,
        "best_activities_distance_activity_id": 9677256645,
        "athlete_firstname": "Sham",
        "athlete_lastname": "H."
    },
    {
        "rank": 3,
        "athlete_id": 61351589,
        "velocity": 3.197898590048038,
        "elev_gain": 291.9688911437988,
        "num_activities": 5,
        "moving_time": 16081,
        "distance": 51425.4072265625,
        "best_activities_distance": 10843.19921875,
        "best_activities_distance_activity_id": 9683886236,
        "athlete_firstname": "Paul",
        "athlete_lastname": "B."
    },
    {
        "rank": 4,
        "athlete_id": 30533086,
        "velocity": 3.386971198213349,
        "elev_gain": 53,
        "num_activities": 3,
        "moving_time": 13342,
        "distance": 45188.9697265625,
        "best_activities_distance": 26589.76953125,
        "best_activities_distance_activity_id": 9670889620,
        "athlete_firstname": "Nicola",
        "athlete_lastname": "M."
    },
    {
        "rank": 5,
        "athlete_id": 4133813,
        "velocity": 3.522659447412538,
        "elev_gain": 169.57999992370605,
        "num_activities": 4,
        "moving_time": 10476,
        "distance": 36903.38037109375,
        "best_activities_distance": 10741.23046875,
        "best_activities_distance_activity_id": 9676725785,
        "athlete_firstname": "Thomas",
        "athlete_lastname": "K."
    },
    {
        "rank": 6,
        "athlete_id": 37776583,
        "velocity": 2.6891421592320492,
        "elev_gain": 663,
        "num_activities": 6,
        "moving_time": 13335,
        "distance": 35859.710693359375,
        "best_activities_distance": 11292.5703125,
        "best_activities_distance_activity_id": 9676430590,
        "athlete_firstname": "Lydia",
        "athlete_lastname": "W."
    },
    {
        "rank": 7,
        "athlete_id": 41554194,
        "velocity": 3.337777826024856,
        "elev_gain": 243,
        "num_activities": 3,
        "moving_time": 8861,
        "distance": 29576.04931640625,
        "best_activities_distance": 16001.0595703125,
        "best_activities_distance_activity_id": 9677066822,
        "athlete_firstname": "Stephen",
        "athlete_lastname": "H."
    },
    {
        "rank": 8,
        "athlete_id": 11743280,
        "velocity": 3.2817342541881445,
        "elev_gain": 38.97973012924194,
        "num_activities": 4,
        "moving_time": 8730,
        "distance": 28649.5400390625,
        "best_activities_distance": 10611.080078125,
        "best_activities_distance_activity_id": 9683173315,
        "athlete_firstname": "Hatty",
        "athlete_lastname": "M."
    },
    {
        "rank": 9,
        "athlete_id": 40425808,
        "velocity": 2.2248309985490367,
        "elev_gain": 561.7629737854004,
        "num_activities": 2,
        "moving_time": 12664,
        "distance": 28175.259765625,
        "best_activities_distance": 17241.4296875,
        "best_activities_distance_activity_id": 9687174526,
        "athlete_firstname": "David",
        "athlete_lastname": "H."
    },
    {
        "rank": 10,
        "athlete_id": 74735797,
        "velocity": 2.4219010531691696,
        "elev_gain": 163.36599349975586,
        "num_activities": 3,
        "moving_time": 11320,
        "distance": 27415.919921875,
        "best_activities_distance": 10998.9794921875,
        "best_activities_distance_activity_id": 9683789753,
        "athlete_firstname": "Blane",
        "athlete_lastname": "M."
    },
    {
        "rank": 11,
        "athlete_id": 2926865,
        "velocity": 2.968080728872643,
        "elev_gain": 74.28654861450195,
        "num_activities": 3,
        "moving_time": 8857,
        "distance": 26288.291015625,
        "best_activities_distance": 11275.8603515625,
        "best_activities_distance_activity_id": 9683674108,
        "athlete_firstname": "Daniel",
        "athlete_lastname": "H."
    },
    {
        "rank": 12,
        "athlete_id": 103056769,
        "velocity": 2.94281935968624,
        "elev_gain": 53.510799407958984,
        "num_activities": 3,
        "moving_time": 8183,
        "distance": 24081.0908203125,
        "best_activities_distance": 10033.400390625,
        "best_activities_distance_activity_id": 9678654980,
        "athlete_firstname": "Marina",
        "athlete_lastname": "E."
    },
    {
        "rank": 13,
        "athlete_id": 13680714,
        "velocity": 3.0229050444606793,
        "elev_gain": 230,
        "num_activities": 3,
        "moving_time": 7229,
        "distance": 21852.58056640625,
        "best_activities_distance": 10056.98046875,
        "best_activities_distance_activity_id": 9650090992,
        "athlete_firstname": "Mike",
        "athlete_lastname": "d."
    },
    {
        "rank": 14,
        "athlete_id": 31691560,
        "velocity": 3.119315745418233,
        "elev_gain": 73,
        "num_activities": 2,
        "moving_time": 6650,
        "distance": 20743.44970703125,
        "best_activities_distance": 13010.1494140625,
        "best_activities_distance_activity_id": 9671039325,
        "athlete_firstname": "Jonathan",
        "athlete_lastname": "S."
    },
    {
        "rank": 15,
        "athlete_id": 29958258,
        "velocity": 2.3641746854182086,
        "elev_gain": 143.38074684143066,
        "num_activities": 4,
        "moving_time": 8106,
        "distance": 19164,
        "best_activities_distance": 6039.60009765625,
        "best_activities_distance_activity_id": 9650028635,
        "athlete_firstname": "Barbara",
        "athlete_lastname": "H."
    },
    {
        "rank": 16,
        "athlete_id": 1696777,
        "velocity": 2.670919703497608,
        "elev_gain": 343,
        "num_activities": 2,
        "moving_time": 7003,
        "distance": 18704.45068359375,
        "best_activities_distance": 10644.640625,
        "best_activities_distance_activity_id": 9670975255,
        "athlete_firstname": "Jack",
        "athlete_lastname": "C."
    },
    {
        "rank": 17,
        "athlete_id": 29577503,
        "velocity": 2.9746383659484175,
        "elev_gain": 125.79946708679199,
        "num_activities": 2,
        "moving_time": 6097,
        "distance": 18136.3701171875,
        "best_activities_distance": 11658.5400390625,
        "best_activities_distance_activity_id": 9647035650,
        "athlete_firstname": "Ian",
        "athlete_lastname": "C."
    },
    {
        "rank": 18,
        "athlete_id": 52884370,
        "velocity": 3.0565743192049015,
        "elev_gain": 71.17226123809814,
        "num_activities": 4,
        "moving_time": 5269,
        "distance": 16105.090087890625,
        "best_activities_distance": 5069.92041015625,
        "best_activities_distance_activity_id": 9651721256,
        "athlete_firstname": "Mairead",
        "athlete_lastname": "H."
    },
    {
        "rank": 19,
        "athlete_id": 50955145,
        "velocity": 2.7484922746033447,
        "elev_gain": 23,
        "num_activities": 2,
        "moving_time": 5830,
        "distance": 16023.7099609375,
        "best_activities_distance": 8013.7099609375,
        "best_activities_distance_activity_id": 9682981339,
        "athlete_firstname": "Miguel",
        "athlete_lastname": "V."
    },
    {
        "rank": 20,
        "athlete_id": 18514233,
        "velocity": 3.2675740878617274,
        "elev_gain": 91.11376571655273,
        "num_activities": 3,
        "moving_time": 4596,
        "distance": 15017.7705078125,
        "best_activities_distance": 5008.490234375,
        "best_activities_distance_activity_id": 9676821156,
        "athlete_firstname": "Freddie",
        "athlete_lastname": "M."
    },
    {
        "rank": 21,
        "athlete_id": 103649447,
        "velocity": 2.488444720664601,
        "elev_gain": 20.967966079711914,
        "num_activities": 3,
        "moving_time": 5729,
        "distance": 14256.2998046875,
        "best_activities_distance": 5074.75,
        "best_activities_distance_activity_id": 9677189154,
        "athlete_firstname": "Hannah",
        "athlete_lastname": "D."
    },
    {
        "rank": 22,
        "athlete_id": 1326614,
        "velocity": 2.6307765992466927,
        "elev_gain": 129.1999969482422,
        "num_activities": 2,
        "moving_time": 4082,
        "distance": 10738.830078125,
        "best_activities_distance": 5705.56005859375,
        "best_activities_distance_activity_id": 9685591544,
        "athlete_firstname": "Mark",
        "athlete_lastname": "T."
    },
    {
        "rank": 23,
        "athlete_id": 58554127,
        "velocity": 3.073306442441085,
        "elev_gain": 71.93500089645386,
        "num_activities": 2,
        "moving_time": 3469,
        "distance": 10661.300048828125,
        "best_activities_distance": 6653,
        "best_activities_distance_activity_id": 9678683236,
        "athlete_firstname": "Dan",
        "athlete_lastname": "B."
    },
    {
        "rank": 24,
        "athlete_id": 6323028,
        "velocity": 2.4921142813554726,
        "elev_gain": 231.15338134765625,
        "num_activities": 2,
        "moving_time": 4148,
        "distance": 10337.2900390625,
        "best_activities_distance": 5335.1201171875,
        "best_activities_distance_activity_id": 9654141009,
        "athlete_firstname": "Sophie",
        "athlete_lastname": "D."
    },
    {
        "rank": 25,
        "athlete_id": 80777288,
        "velocity": 2.838265855233009,
        "elev_gain": 16.65000057220459,
        "num_activities": 2,
        "moving_time": 3546,
        "distance": 10064.49072265625,
        "best_activities_distance": 5040.17041015625,
        "best_activities_distance_activity_id": 9664721072,
        "athlete_firstname": "Lorna",
        "athlete_lastname": "C."
    },
    {
        "rank": 26,
        "athlete_id": 100745857,
        "velocity": 3.1479127161711165,
        "elev_gain": 50,
        "num_activities": 2,
        "moving_time": 3090,
        "distance": 9727.05029296875,
        "best_activities_distance": 5011.830078125,
        "best_activities_distance_activity_id": 9646322098,
        "athlete_firstname": "Alison",
        "athlete_lastname": "L."
    },
    {
        "rank": 27,
        "athlete_id": 1908509,
        "velocity": 2.919025856870526,
        "elev_gain": 258,
        "num_activities": 1,
        "moving_time": 3213,
        "distance": 9378.830078125,
        "best_activities_distance": 9378.830078125,
        "best_activities_distance_activity_id": 9686912830,
        "athlete_firstname": "Josh",
        "athlete_lastname": "B."
    },
    {
        "rank": 28,
        "athlete_id": 57678895,
        "velocity": 2.8200759358750824,
        "elev_gain": 113.47991561889648,
        "num_activities": 2,
        "moving_time": 3029,
        "distance": 8542.010009765625,
        "best_activities_distance": 5241.580078125,
        "best_activities_distance_activity_id": 9672656844,
        "athlete_firstname": "Nico",
        "athlete_lastname": "M."
    },
    {
        "rank": 29,
        "athlete_id": 2095180,
        "velocity": 3.6785747842427616,
        "elev_gain": 35,
        "num_activities": 1,
        "moving_time": 2245,
        "distance": 8258.400390625,
        "best_activities_distance": 8258.400390625,
        "best_activities_distance_activity_id": 9653386524,
        "athlete_firstname": "David",
        "athlete_lastname": "S."
    },
    {
        "rank": 30,
        "athlete_id": 21014702,
        "velocity": 3.865878174399883,
        "elev_gain": 32,
        "num_activities": 1,
        "moving_time": 1708,
        "distance": 6602.919921875,
        "best_activities_distance": 6602.919921875,
        "best_activities_distance_activity_id": 9647608217,
        "athlete_firstname": "Tom",
        "athlete_lastname": "M."
    },
    {
        "rank": 31,
        "athlete_id": 7347389,
        "velocity": 2.6945504670095914,
        "elev_gain": 97,
        "num_activities": 1,
        "moving_time": 2424,
        "distance": 6531.59033203125,
        "best_activities_distance": 6531.59033203125,
        "best_activities_distance_activity_id": 9652983191,
        "athlete_firstname": "David",
        "athlete_lastname": "T."
    },
    {
        "rank": 32,
        "athlete_id": 19471594,
        "velocity": 2.673499389491198,
        "elev_gain": 36,
        "num_activities": 1,
        "moving_time": 2329,
        "distance": 6226.580078125,
        "best_activities_distance": 6226.580078125,
        "best_activities_distance_activity_id": 9687819042,
        "athlete_firstname": "Chris",
        "athlete_lastname": "C."
    },
    {
        "rank": 33,
        "athlete_id": 23175006,
        "velocity": 3.397872784815797,
        "elev_gain": 60.28433609008789,
        "num_activities": 1,
        "moving_time": 1744,
        "distance": 5925.89013671875,
        "best_activities_distance": 5925.89013671875,
        "best_activities_distance_activity_id": 9670643018,
        "athlete_firstname": "Aksel Strandgaard",
        "athlete_lastname": "H."
    },
    {
        "rank": 34,
        "athlete_id": 27329211,
        "velocity": 2.720736394664329,
        "elev_gain": 83.00824737548828,
        "num_activities": 1,
        "moving_time": 1996,
        "distance": 5430.58984375,
        "best_activities_distance": 5430.58984375,
        "best_activities_distance_activity_id": 9659336470,
        "athlete_firstname": "Christian",
        "athlete_lastname": "P."
    },
    {
        "rank": 35,
        "athlete_id": 30636088,
        "velocity": 2.606114157347026,
        "elev_gain": 0,
        "num_activities": 1,
        "moving_time": 2051,
        "distance": 5345.14013671875,
        "best_activities_distance": 5345.14013671875,
        "best_activities_distance_activity_id": 9686592903,
        "athlete_firstname": "Dave",
        "athlete_lastname": "C."
    },
    {
        "rank": 36,
        "athlete_id": 115586574,
        "velocity": 3.5613677135010633,
        "elev_gain": 4.430769443511963,
        "num_activities": 1,
        "moving_time": 1411,
        "distance": 5025.08984375,
        "best_activities_distance": 5025.08984375,
        "best_activities_distance_activity_id": 9678320060,
        "athlete_firstname": "Lewis",
        "athlete_lastname": "J."
    },
    {
        "rank": 37,
        "athlete_id": 24392844,
        "velocity": 2.805492290181068,
        "elev_gain": 30.691682815551758,
        "num_activities": 1,
        "moving_time": 1788,
        "distance": 5016.22021484375,
        "best_activities_distance": 5016.22021484375,
        "best_activities_distance_activity_id": 9651722373,
        "athlete_firstname": "Hannah",
        "athlete_lastname": "M."
    },
    {
        "rank": 38,
        "athlete_id": 44138705,
        "velocity": 2.634262458747278,
        "elev_gain": 22,
        "num_activities": 1,
        "moving_time": 1837,
        "distance": 4839.14013671875,
        "best_activities_distance": 4839.14013671875,
        "best_activities_distance_activity_id": 9677239337,
        "athlete_firstname": "Ellie",
        "athlete_lastname": "H."
    },
    {
        "rank": 39,
        "athlete_id": 15378121,
        "velocity": 3.1361029451245703,
        "elev_gain": 16.073749542236328,
        "num_activities": 1,
        "moving_time": 1455,
        "distance": 4563.02978515625,
        "best_activities_distance": 4563.02978515625,
        "best_activities_distance_activity_id": 9664808054,
        "athlete_firstname": "David",
        "athlete_lastname": "S."
    }
]
